{
  "Top": "singlecycle_riscv",
  "RtlTop": "singlecycle_riscv",
  "RtlPrefix": "",
  "SourceLanguage": "cpp",
  "ResetStyle": "control",
  "GenerateBdFiles": "0",
  "HostMachineBits": "64",
  "Target": {
    "Family": "zynq",
    "Device": "xc7z020",
    "Package": "clg484",
    "Speed": "-1"
  },
  "HlsSolution": {
    
  },
  "ClockInfo": {
    "ClockName": "ap_clk",
    "ClockPeriod": "10",
    "IsCombLogic": "0",
    "II": "x",
    "Latency": "17",
    "Uncertainty": "1.25"
  },
  "Xdc": {"OocClocks": ["create_clock -name ap_clk -period 10.000 [get_ports ap_clk]"]},
  "Ipx": {
    "Vendor": "xilinx.com",
    "Library": "hls",
    "Name": "singlecycle_riscv",
    "Version": "1.0",
    "DisplayName": "Singlecycle_riscv",
    "Description": "An IP generated by Vivado HLS",
    "Taxonomy": "\/VIVADO_HLS_IP"
  },
  "Files": {
    "CSource": [
      "..\/ins_memory.cpp",
      "..\/data_memory.cpp",
      "..\/GReg.cpp",
      "..\/ALU.cpp"
    ],
    "Vhdl": [
      "impl\/vhdl\/singlecycle_riscvbkb.vhd",
      "impl\/vhdl\/singlecycle_riscvcud.vhd",
      "impl\/vhdl\/singlecycle_riscv.vhd"
    ],
    "Verilog": [
      "impl\/verilog\/singlecycle_riscvbkb.v",
      "impl\/verilog\/singlecycle_riscvbkb_rom.dat",
      "impl\/verilog\/singlecycle_riscvcud.v",
      "impl\/verilog\/singlecycle_riscv.v"
    ],
    "Misc": ["impl\/misc\/logo.png"]
  },
  "SubcoreInfo": {
    "HasXpmMemory": false,
    "HasClockedDsp": false,
    "IP": []
  },
  "Interfaces": {
    "ap_clk": {
      "type": "clock",
      "ctype": {"CLK": {"Type": "bool"}},
      "reset": "ap_rst"
    },
    "ap_ctrl": {
      "type": "ap_ctrl",
      "ctrl_ports": "ap_start ap_done ap_idle ap_ready",
      "ctype": {
        "start": {"Type": "bool"},
        "done": {"Type": "bool"},
        "idle": {"Type": "bool"},
        "ready": {"Type": "bool"}
      }
    },
    "ap_rst": {
      "type": "reset",
      "polarity": "ACTIVE_HIGH",
      "ctype": {"RST": {"Type": "bool"}}
    },
    "immediate_V": {
      "type": "data",
      "dir": "in",
      "width": "6",
      "ctype": {"DATA": {
          "Type": "integer signed",
          "Width": "6"
        }}
    },
    "startingInst_V": {
      "type": "data",
      "dir": "in",
      "width": "32",
      "ctype": {"DATA": {
          "Type": "integer signed",
          "Width": "32"
        }}
    }
  },
  "RtlPorts": {
    "ap_clk": {
      "dir": "in",
      "width": "1"
    },
    "ap_rst": {
      "dir": "in",
      "width": "1"
    },
    "ap_start": {
      "dir": "in",
      "width": "1"
    },
    "ap_done": {
      "dir": "out",
      "width": "1"
    },
    "ap_idle": {
      "dir": "out",
      "width": "1"
    },
    "ap_ready": {
      "dir": "out",
      "width": "1"
    },
    "startingInst_V": {
      "dir": "in",
      "width": "32"
    },
    "startingInst_V_ap_vld": {
      "dir": "in",
      "width": "1"
    },
    "startingInst_V_ap_ack": {
      "dir": "out",
      "width": "1"
    },
    "immediate_V": {
      "dir": "in",
      "width": "6"
    },
    "immediate_V_ap_vld": {
      "dir": "in",
      "width": "1"
    },
    "immediate_V_ap_ack": {
      "dir": "out",
      "width": "1"
    }
  },
  "CPorts": {
    "ap_ctrl": {
      "interfaceRef": "ap_ctrl",
      "dir": "out"
    },
    "startingInst_V": {
      "interfaceRef": "startingInst_V",
      "dir": "in",
      "dataWidth": "32",
      "handshakeRef": "ap_hs"
    },
    "immediate_V": {
      "interfaceRef": "immediate_V",
      "dir": "in",
      "dataWidth": "6",
      "handshakeRef": "ap_hs"
    }
  },
  "ModuleInfo": {
    "Hierarchy": {"ModuleName": "singlecycle_riscv"},
    "Metrics": {"singlecycle_riscv": {
        "Latency": {
          "LatencyBest": "17",
          "LatencyAvg": "17",
          "LatencyWorst": "17",
          "PipelineII": "18",
          "PipelineDepth": "",
          "PipelineType": "none"
        },
        "Timing": {
          "Target": "10.00",
          "Uncertainty": "1.25",
          "Estimate": "6.49"
        },
        "Loops": [{
            "Name": "Loop 1",
            "TripCount": "15",
            "Latency": "15",
            "PipelineII": "",
            "PipelineDepth": "1"
          }],
        "Area": {
          "BRAM_18K": "0",
          "FF": "28",
          "LUT": "172",
          "DSP48E": "0"
        }
      }}
  },
  "GenData": {
    "DataVersion": "0.1",
    "Time": "2018-02-25 17:21:31 +0100",
    "ToolName": "vivado_hls",
    "ToolVersion": "2017.4"
  }
}
